daqcrux/R5218.py
daqcrux/__init__.py
daqcrux/adc.py
daqcrux/airmar.py
daqcrux/ais.py
daqcrux/aquadopp.py
daqcrux/aquatroll.py
daqcrux/client.py
daqcrux/functions.py
daqcrux/hyperion.py
daqcrux/message.py
daqcrux/modbus.py
daqcrux/test.py
daqcrux-0.1.1.dist-info/METADATA
daqcrux-0.1.1.dist-info/WHEEL
daqcrux-0.1.1.dist-info/top_level.txt
daqcrux-0.1.1.dist-info/RECORD
